gists/__init__.py
gists/client.py
gists/constants.py
gists/exceptions.py
gists/file.py
gists/gist.py
github_gists-1.2.1.dist-info/LICENSE
github_gists-1.2.1.dist-info/METADATA
github_gists-1.2.1.dist-info/WHEEL
github_gists-1.2.1.dist-info/top_level.txt
github_gists-1.2.1.dist-info/RECORD
