Metadata-Version: 2.1
Name: github-gists
Version: 1.2.1
Summary: A simple asynchronous python wrapper for the GitHub Gists API
Home-page: https://github.com/WitherredAway/gists.py
Author: Witherr
Author-email: sdssouvic99@gmail.com
License: GPL-3.0
Project-URL: Issue Tracker, https://github.com/WitherredAway/gists.py/issues
Platform: UNKNOWN
Classifier: License :: OSI Approved :: GNU General Public License v3 (GPLv3)
Classifier: Operating System :: OS Independent
Classifier: Programming Language :: Python :: 3
Classifier: Programming Language :: Python :: 3 :: Only
Classifier: Programming Language :: Python :: 3.8
Classifier: Programming Language :: Python :: 3.9
Classifier: Programming Language :: Python :: 3.10
Requires-Python: >=3.8
License-File: LICENSE
Requires-Dist: aiohttp (==3.8.1)
